flake8_classmethod_staticmethod/__init__.py
flake8_classmethod_staticmethod/checker.py
flake8_classmethod_staticmethod-2.1.dist-info/LICENSE
flake8_classmethod_staticmethod-2.1.dist-info/METADATA
flake8_classmethod_staticmethod-2.1.dist-info/WHEEL
flake8_classmethod_staticmethod-2.1.dist-info/entry_points.txt
flake8_classmethod_staticmethod-2.1.dist-info/top_level.txt
flake8_classmethod_staticmethod-2.1.dist-info/RECORD
