Metadata-Version: 2.1
Name: flake8-classmethod-staticmethod
Version: 2.1
Summary: flake8 plugin that checks rules regarding the staticmethod and classmethod decorators.
Home-page: https://github.com/atollk/flake8-classmethod-staticmethod
Author: Andreas Tollkötter
License: MIT
Keywords: flake8,classmethod,staticmethod
Classifier: Framework :: Flake8
Classifier: Intended Audience :: Developers
Classifier: License :: OSI Approved :: MIT License
Classifier: Natural Language :: English
Classifier: Programming Language :: Python :: 3 :: Only
Classifier: Programming Language :: Python :: 3
Classifier: Programming Language :: Python :: 3.8
Classifier: Programming Language :: Python :: 3.9
Classifier: Programming Language :: Python :: 3.10
Classifier: Programming Language :: Python :: 3.11
Classifier: Programming Language :: Python :: 3.12
Requires-Python: >=3.8
License-File: LICENSE
